{
 "creation": "2020-06-16 03:32:34.556514",
 "doctype": "DocType",
 "editable_grid": 1,
 "engine": "InnoDB",
 "field_order": [
  "role_stock_entry"
 ],
 "fields": [
  {
   "fieldname": "role_stock_entry",
   "fieldtype": "Link",
   "in_list_view": 1,
   "label": "Role",
   "options": "Role"
  }
 ],
 "istable": 1,
 "modified": "2020-06-16 03:32:34.556514",
 "modified_by": "Administrator",
 "module": "Addon Customization",
 "name": "Setting Child Role Stock",
 "owner": "Administrator",
 "permissions": [],
 "quick_entry": 1,
 "sort_field": "modified",
 "sort_order": "DESC",
 "track_changes": 1
}